deepdanbooru_onnx/__init__.py
deepdanbooru_onnx/deepdanbooru_onnx.py
deepdanbooru_onnx-0.0.7.dist-info/LICENSE
deepdanbooru_onnx-0.0.7.dist-info/METADATA
deepdanbooru_onnx-0.0.7.dist-info/WHEEL
deepdanbooru_onnx-0.0.7.dist-info/top_level.txt
deepdanbooru_onnx-0.0.7.dist-info/RECORD
