Metadata-Version: 2.1
Name: deepdanbooru-onnx
Version: 0.0.7
Summary: anime image classification
Home-page: https://github.com/chinoll/deepdanbooru_onnx
Author: chinoll
Author-email: chinoll@chinoll.org
License: UNKNOWN
Keywords: deepdanbooru,anime,image classification,onnx,deep learning
Platform: UNKNOWN
Classifier: License :: OSI Approved :: GNU General Public License v3 (GPLv3)
Classifier: Programming Language :: Python :: 3 :: Only
Classifier: Operating System :: OS Independent
Requires: onnx
Requires: onnxruntime
Requires: tqdm
Requires: numpy
Requires: Pillow
Requires: requests
Requires: shutil
Requires: hashlib
Requires: os
Requires-Dist: onnx
Requires-Dist: onnxruntime
Requires-Dist: tqdm
Requires-Dist: numpy
Requires-Dist: pillow
Requires-Dist: requests
